{
    "about":"Games, websites, tools, anything written with code",
    "description":"Games, websites, tools, and other software. Most of it is written for browsers in JavaScript as it runs easily on multiple platforms and is ideal for portfolio projects.",
    "branches":[
        "Sites",
        "Standalone",
        "Lost Projects"
    ],

    "styling":{
        "text_color":[200, 255, 200],
        "bg_size":2000,
        "background":"/assets/backgrounds/code.png",
        "column_border_color":[0, 255, 0, 1]
    }
}